django_jalali/__init__.py
django_jalali/models.py
django_jalali/admin/__init__.py
django_jalali/admin/filters.py
django_jalali/admin/filterspecs.py
django_jalali/admin/widgets.py
django_jalali/db/__init__.py
django_jalali/db/models.py
django_jalali/forms/__init__.py
django_jalali/forms/widgets.py
django_jalali/serializers/__init__.py
django_jalali/serializers/serializerfield.py
django_jalali/static/admin/main.js
django_jalali/static/admin/css/main.css
django_jalali/static/admin/jquery.ui.datepicker.jalali/default.htm
django_jalali/static/admin/jquery.ui.datepicker.jalali/scripts/calendar.all.js
django_jalali/static/admin/jquery.ui.datepicker.jalali/scripts/calendar.js
django_jalali/static/admin/jquery.ui.datepicker.jalali/scripts/jquery-1.10.2.min.js
django_jalali/static/admin/jquery.ui.datepicker.jalali/scripts/jquery-1.10.2.min.map
django_jalali/static/admin/jquery.ui.datepicker.jalali/scripts/jquery.ui.core.js
django_jalali/static/admin/jquery.ui.datepicker.jalali/scripts/jquery.ui.datepicker-cc-fa.js
django_jalali/static/admin/jquery.ui.datepicker.jalali/scripts/jquery.ui.datepicker-cc.js
django_jalali/static/admin/jquery.ui.datepicker.jalali/themes/base/.DS_Store
django_jalali/static/admin/jquery.ui.datepicker.jalali/themes/base/jquery-ui.css
django_jalali/static/admin/jquery.ui.datepicker.jalali/themes/base/jquery-ui.min.css
django_jalali/static/admin/jquery.ui.datepicker.jalali/themes/base/jquery.ui.theme.css
django_jalali/static/admin/jquery.ui.datepicker.jalali/themes/base/images/animated-overlay.gif
django_jalali/static/admin/jquery.ui.datepicker.jalali/themes/base/images/icon-calendar.svg
django_jalali/static/admin/jquery.ui.datepicker.jalali/themes/base/images/ui-bg_flat_30_cccccc_40x100.png
django_jalali/static/admin/jquery.ui.datepicker.jalali/themes/base/images/ui-bg_flat_50_5c5c5c_40x100.png
django_jalali/static/admin/jquery.ui.datepicker.jalali/themes/base/images/ui-bg_glass_20_555555_1x400.png
django_jalali-7.2.0.dist-info/LICENSE
django_jalali-7.2.0.dist-info/METADATA
django_jalali-7.2.0.dist-info/WHEEL
django_jalali-7.2.0.dist-info/top_level.txt
django_jalali-7.2.0.dist-info/RECORD
