Metadata-Version: 2.1
Name: django-jalali
Version: 7.2.0
Summary: Jalali Date support for Django model and admin interface
Home-page: http://github.com/slashmili/django-jalali
Download-URL: http://github.com/slashmili/django-jalali/tarball/master
Author: Milad Rastian
Author-email: eslashmili@gmail.com
License: Python Software Foundation License
Keywords: django jalali
Platform: any
Classifier: Development Status :: 5 - Production/Stable
Classifier: Intended Audience :: Developers
Classifier: License :: OSI Approved :: BSD License
Classifier: Operating System :: OS Independent
Classifier: Programming Language :: Python
Classifier: Programming Language :: Python :: 3
Classifier: Programming Language :: Python :: 3.8
Classifier: Programming Language :: Python :: 3.9
Classifier: Programming Language :: Python :: 3.10
Classifier: Programming Language :: Python :: 3.11
Classifier: Programming Language :: Python :: 3.12
Classifier: Programming Language :: Python :: Implementation :: CPython
Classifier: Framework :: Django
Classifier: Framework :: Django :: 4.2
Classifier: Framework :: Django :: 5.0
Classifier: Framework :: Django :: 5.1
License-File: LICENSE
Requires-Dist: jdatetime>=5.0.0
Requires-Dist: django>=4.2
Provides-Extra: drf
Requires-Dist: djangorestframework>=3.12; extra == "drf"
